flass/__init__.py
flass/cli.py
flass/model.py
flass-0.1.11.dist-info/LICENSE
flass-0.1.11.dist-info/METADATA
flass-0.1.11.dist-info/WHEEL
flass-0.1.11.dist-info/entry_points.txt
flass-0.1.11.dist-info/top_level.txt
flass-0.1.11.dist-info/RECORD
