Metadata-Version: 2.1
Name: flass
Version: 0.1.11
Summary: Train Keras Convolutional Neural Network for image classification
Home-page: http://flikka.net
Author: Kristian Flikka
Author-email: kristian.flikka@gmail.com
License: MIT
Platform: UNKNOWN
Classifier: Intended Audience :: Developers
Classifier: Programming Language :: Python :: 3.8
Requires-Dist: azure-storage-blob
Requires-Dist: click
Requires-Dist: graphviz
Requires-Dist: matplotlib
Requires-Dist: mlflow
Requires-Dist: numpy
Requires-Dist: pandas
Requires-Dist: pydot
Requires-Dist: sklearn
Requires-Dist: scikit-image
Requires-Dist: tensorflow
Provides-Extra: lime
Requires-Dist: lime ; extra == 'lime'
